[
  {
    "id": "fire-warrior",
    "title": "Guerreiro do fogo",
    "description": "Um guerreiro forjado nas chamas do abismo, empunha lâminas incandescentes que cauterizam a carne e o espírito. Onde seus passos ecoam, o fogo se torna lei.",
    "speed": 1,
    "moveType": "slow",
    "power": 3,
    "range": 1,
    "health": 10,
    "defense": 2,
    "image": "assets/imgs/cards/fire-warrior.png",
    "type": "creature",
    "element": "fire",
    "attackType": "elemental",
    "effects": [
      {
        "type": "burn",
        "trigger": "onAttack"
      },
      {
        "type": "buff",
        "trigger": "onPlay"
      }
    ],
    "manaCost": 1,
    "skillIds": ["flame-burst"]
  },
  {
    "id": "phoenix-ember",
    "title": "Phoenix Ember",
    "description": "Renascida das cinzas em brasa, esta criatura alada irradia calor e majestade. Seus cantos ecoam esperança, enquanto suas penas ardem com o fogo da eternidade.",
    "speed": 2,
    "moveType": "agile",
    "power": 2,
    "range": 1,
    "health": 9,
    "defense": 2,
    "image": "assets/imgs/cards/phoenix-ember.png",
    "type": "creature",
    "element": "fire",
    "attackType": "elemental",
    "effects": [
      {
        "type": "heal",
        "trigger": "onDeath"
      },
      {
        "type": "buff",
        "trigger": "onDeath"
      }
    ],
    "manaCost": 10
  },
  {
    "id": "scorchnub",
    "title": "Scorchnub",
    "description": "Pequeno, redondo e fervilhante, este ser de magma rasteja pelas crateras deixando um rastro fumegante. Sua inocência é uma armadilha: sua explosão repentina pode ser fatal.",
    "speed": 1,
    "moveType": "slow",
    "power": 2,
    "range": 1,
    "health": 4,
    "defense": 2,
    "image": "assets/imgs/cards/scorchnub.png",
    "type": "creature",
    "element": "fire",
    "attackType": "physical",
    "effects": [
      {
        "type": "burn",
        "trigger": "onDeath"
      }
    ],
    "manaCost": 5
  },
  {
    "id": "rubisscale",
    "title": "Rubisscale",
    "description": "Criada nas cavernas vulcânicas, esta serpente desliza em silêncio até atacar com labaredas das presas. Suas escamas rubi são tão resistentes quanto afiadas.",
    "speed": 2,
    "moveType": "agile",
    "power": 2,
    "range": 1,
    "health": 7,
    "defense": 3,
    "image": "assets/imgs/cards/rubisscale.png",
    "type": "creature",
    "element": "fire",
    "attackType": "elemental",
    "effects": [
      {
        "type": "burn",
        "trigger": "onAttack"
      },
      {
        "type": "burn",
        "trigger": "onAttack"
      }
    ],
    "manaCost": 6,
    "skillIds": [
      "flame-burst",
      "flame-burst-1",
      "flame-burst-2",
      "flame-burst-3"
    ]
  },
  {
    "id": "moltarok",
    "title": "Moltarok",
    "description": "Dizem que Moltarok foi forjado nas chamas do próprio coração da terra. Com seu machado flamejante, corta inimigos como manteiga derretida, espalhando brasas a cada golpe.",
    "speed": 2,
    "moveType": "slow",
    "power": 6,
    "range": 1,
    "health": 9,
    "defense": 2,
    "image": "assets/imgs/cards/moltarok.png",
    "type": "creature",
    "element": "fire",
    "attackType": "physical",
    "effects": [],
    "manaCost": 11
  },
  {
    "id": "frost-spirit",
    "title": "Espirito de Gelo",
    "description": "Essa criatura etérea dos ventos do norte desliza sobre o campo de batalha como névoa gélida. Onde passa, o frio paralisa, congelando até a coragem dos inimigos.",
    "speed": 2,
    "moveType": "agile",
    "power": 1,
    "range": 2,
    "health": 6,
    "defense": 1,
    "image": "assets/imgs/cards/frost-spirit.png",
    "type": "creature",
    "element": "ice",
    "attackType": "elemental",
    "effects": [
      {
        "type": "freeze",
        "trigger": "onAttack"
      }
    ],
    "manaCost": 1
  },
  {
    "id": "stone-guardian",
    "title": "Guardião de Pedra",
    "description": "Criado das entranhas da terra, este colosso de pedra vive para proteger. Imponente e inabalável, fortalece os aliados ao seu redor com sua presença ancestral.",
    "speed": 1,
    "moveType": "slow",
    "power": 1,
    "range": 1,
    "health": 12,
    "defense": 4,
    "image": "assets/imgs/cards/stone-guardian.png",
    "type": "creature",
    "element": "nature",
    "attackType": "physical",
    "effects": [
      {
        "type": "buff",
        "trigger": "onTurnStart"
      }
    ],
    "manaCost": 1
  },
  {
    "id": "arcane-spirit",
    "title": "Espirito Mágico",
    "description": "Criatura efêmera forjada em magia pura, seu corpo cintila como cristal à luz roxa. Paira no ar sem forma definida, sussurrando mistérios de um poder ancestral.",
    "speed": 1,
    "moveType": "slow",
    "power": 4,
    "range": 2,
    "health": 3,
    "defense": 0,
    "image": "assets/imgs/cards/arcane-spirit.png",
    "type": "creature",
    "element": "light",
    "attackType": "explosion",
    "effects": [
      {
        "type": "debuff",
        "trigger": "onPlay"
      },
      {
        "type": "burn",
        "trigger": "onPlay"
      }
    ],
    "manaCost": 1
  },
  {
    "id": "shadow-rider",
    "title": "Shadow Rider",
    "description": "Montado em um corcel envolto em trevas, este cavaleiro espectral surge das sombras com rapidez sobrenatural. Seus olhos brilham como brasas na noite eterna.",
    "speed": 3,
    "moveType": "agile",
    "power": 2,
    "range": 1,
    "health": 7,
    "defense": 1,
    "image": "assets/imgs/cards/shadow-rider.png",
    "type": "creature",
    "element": "shadow",
    "attackType": "physical",
    "effects": [
      {
        "type": "buff",
        "trigger": "onAttack"
      },
      {
        "type": "heal",
        "trigger": "onAttack"
      }
    ],
    "manaCost": 1
  },
  {
    "id": "blizzard-field",
    "title": "Nevasca",
    "description": "Uma nevasca implacável toma o campo, cobrindo tudo com um véu de gelo e silêncio. O mundo se cala sob o domínio do inverno eterno.",
    "speed": 0,
    "moveType": "slow",
    "power": 0,
    "range": 0,
    "health": 0,
    "defense": 0,
    "image": "assets/imgs/cards/blizzard-field.png",
    "type": "field",
    "background": "assets/imgs/cards/blizzard-field.png",
    "fieldEffects": [
      {
        "element": "ice",
        "modifier": 2
      },
      {
        "element": "nature",
        "modifier": 0.5
      }
    ],
    "manaCost": 2
  },
  {
    "id": "inferno-field",
    "title": "Campos do Inferno",
    "description": "Chamas intensas dominam o terreno, fortalecendo fogo e enfraquecendo gelo.",
    "speed": 0,
    "moveType": "slow",
    "power": 0,
    "range": 0,
    "health": 0,
    "defense": 0,
    "image": "assets/imgs/cards/inferno-field.png",
    "type": "field",
    "background": "assets/imgs/cards/inferno-field.png",
    "fieldEffects": [
      {
        "element": "fire",
        "modifier": 2
      },
      {
        "element": "ice",
        "modifier": 0.5
      }
    ],
    "manaCost": 2
  },
  {
    "id": "flower-field",
    "title": "Campo Florido",
    "description": "",
    "speed": 0,
    "moveType": "slow",
    "power": 0,
    "range": 0,
    "health": 0,
    "defense": 0,
    "image": "assets/imgs/cards/flower-field.png",
    "type": "field",
    "background": "assets/imgs/cards/flower-field.png",
    "fieldEffects": [
      {
        "element": "nature",
        "modifier": 2
      },
      {
        "element": "fire",
        "modifier": 0.5
      }
    ],
    "manaCost": 2
  }
]
